genai_client/__init__.py
genai_client/client.py
genai_client/py.typed
genai_client-0.1.2.dist-info/METADATA
genai_client-0.1.2.dist-info/WHEEL
genai_client-0.1.2.dist-info/licenses/LICENSE
genai_client-0.1.2.dist-info/RECORD
