Metadata-Version: 2.4
Name: genai-client
Version: 0.1.2
Summary: Unified minimal client for OpenAI and Google Gemini responses
Author: indumathi
License: MIT
License-File: LICENSE
Requires-Python: >=3.10
Requires-Dist: google-genai>=1.31.0
Requires-Dist: openai>=1.101.0
Requires-Dist: python-dotenv>=1.1.1
Requires-Dist: twine>=6.1.0
